archivos_verilog/spi_data_order.v
module spi_data_order#(
	parameter DATA_WIDTH = 32
)(
	input rst,
	input en,
	input [DATA_WIDTH-1:0] SPI_DATA_IN,
	input SPI_BIT_ORDER,
	output reg [DATA_WIDTH-1:0] SPI_DATA_OUT
);
	//Se cambia el orden de los bits segun SPI_BIT_ORDER

	integer i;
	always @(*) 
	begin
	if (rst) begin
	    SPI_DATA_OUT <= 0;
	end else begin
	  if (en) begin
	   if (SPI_BIT_ORDER) begin
	   	for (i = 0; i < DATA_WIDTH; i = i+1) begin
	   	   SPI_DATA_OUT[i] <= SPI_DATA_IN[DATA_WIDTH - 1 - i];
	   	end
	   end else begin
	   	SPI_DATA_OUT <= SPI_DATA_IN;
	       end
	  end 
	end
	end

endmodule

archivos_verilog/logic master/piso_sipo.v
module piso_sipo#(
    parameter DATA_WIDTH = 32  // Ancho de los datos, configurable por el usuario
)(
    input clk,                  // Reloj del sistema
    input rst,                  // Señal de reinicio
    input load,                 // Señal para cargar nuevos datos
    input [DATA_WIDTH-1:0] data_in, // Entrada paralela de datos
    input MISO,                 // Entrada serial para recibir datos
    input [1:0] SPI_DATA_LEN,   // Configuración del ancho de datos SPI
    output reg done,            // Señal que indica cuando la operación ha terminado
    output reg MOSI,            // Salida serial para enviar datos
    output reg [DATA_WIDTH-1:0] data_out, // Salida paralela de datos recibidos
    output reg load_data_in     // Señal para cargar nuevos datos a `shift_reg`
);
   
    // Registro de desplazamiento para transmisión y recepción serial
    reg [DATA_WIDTH-1:0] shift_reg;
    reg [$clog2(DATA_WIDTH):0] couter_bit;   // Contador de bits transmitidos/recibidos
    wire [4:0] data_len;                     // Longitud de datos configurada según SPI_DATA_LEN

    // Bloque secuencial principal para manejar el envío y recepción de datos
    always @(posedge clk or posedge rst)
    begin
        if (rst) begin
            // Reset: Inicialización de registros y señales
            shift_reg <= 0;
            couter_bit <= 0;   // Inicializado fuera del rango para detener actividad
            MOSI <= 0;
            data_out <= 0;
            done <= 0;
        end else begin
            if (load) begin
		    if (couter_bit < (DATA_WIDTH - data_len)) begin
		    	/*if (couter_bit == 0) begin
		        shift_reg <= data_in;     // Cargar datos paralelos en el registro
		        //couter_bit <= 1;
		        done <= 0;
		    	end*/
		        // Envío y recepción serial:
		        MOSI <= shift_reg[0]; 			         // Enviar el bit menos significativo
		        shift_reg <= (shift_reg >> 1);                   // Desplazar bits a la derecha
		        shift_reg[(DATA_WIDTH - data_len) - 1] <= MISO;  // Recibir bit del MISO
		        couter_bit <= couter_bit + 1;                    // Incrementar el contador de bits
		        done <= 0;
		    end else begin
		        // Operación terminada:
		        data_out <= shift_reg; // Cargar el contenido recibido en la salida paralela
		        done <= 1;             // Indicar que la operación ha finalizado
		        MOSI <= 0;             // Deshabilitar la salida serial
		        //couter_bit <= 33;
            		end
            end else begin
		MOSI <= 0;
                //done <= 0;
            	shift_reg <= data_in;
            end
        end
    end
    
    
    
    // Bloque combinacional para cargar datos iniciales y configurar longitud de datos
    assign data_len = (SPI_DATA_LEN == 2'b00) ? 5'd24 :
                      (SPI_DATA_LEN == 2'b01) ? 5'd16 :
                      (SPI_DATA_LEN == 2'b10) ? 5'd8  : 5'd0;  // Para 2'b11 o cualquier otro valor
	
endmodule

archivos_verilog/divider clock/divider_clock_spi.v
module divider_clock_spi(
    input clk_cpu,           // Señal de reloj principal del CPU
    input rst,               // Señal de reinicio
    input en,                // Habilitación del divisor de reloj
    input [31:0] spi_bitrate, // Valor del bitrate deseado para SPI (controla la frecuencia del reloj SCK)
    output reg SCK           // Señal de reloj SCK generada
);

    //Se realiza un contador en cada pulso de reloj_CPU que depende del bitrate, 
    //con el fin de generar una nueva señal con una frecuencia dividida comparandola con la de la CPU,
    //esto permite que el usuario tenga control de la velocidad de transmision
	
	
    // Contador para dividir la frecuencia del reloj `clk_cpu`
    integer counter = 0;
	
    // Bloque siempre activo en el flanco positivo del reloj `clk_cpu` o al activarse `rst`
    always @(posedge clk_cpu or posedge rst) 
    begin
        if (rst) begin
            // Reinicio: Inicializar contador y señal SCK
            counter <= 0;
            SCK <= 0;
        end else begin
            if (en) begin
                // Si la habilitación está activa (`en`):
                if (counter == spi_bitrate - 1) begin
                    // Si el contador alcanza el valor deseado (basado en `spi_bitrate`):
                    counter <= 0;       // Reiniciar el contador
                    SCK <= ~SCK;        // Invertir el estado de la señal SCK (generar el siguiente flanco)
                end else begin
                    // Incrementar el contador en cada ciclo
                    counter <= counter + 1;
                end
            end else begin
                // Si no está habilitado (`en`), mantener SCK en bajo
                SCK <= 0;
            end
        end
    end
endmodule

archivos_verilog/spi_control.v
module spi_control(
	input clk_cpu,
	input rst,
	input [31:0] SPI_BITRATE,
	input [31:0] SPI_DATA_OUT,
	output wire [31:0] SPI_DATA_IN,
	input [8:0] SPI_CTRL,
	output SCK,
	output wire MOSI,
	input MISO,
	output SS,
	output reg interrpt
);

	//Parametros para los estados de la maquina
	parameter IDLE = 3'b000;
	parameter LOAD = 3'b001;
	parameter TRANSMIT = 3'b010;
	parameter DONE = 3'b011;
	parameter FRAME_STOP = 3'b100;
	
	//variables para manejar los estados
	reg [2:0] corrent_state, next_state;
	
	//Ordenar los bit del registro SPI_CTRL
	wire SPI_ON = SPI_CTRL[8];
	wire [1:0] SPI_MODE = SPI_CTRL[7:6];
	wire SPI_BIT_ORDER = SPI_CTRL[5];
	wire [1:0] SPI_DATA_LEN = SPI_CTRL[4:3];
	wire SPI_FRAME_START = SPI_CTRL[2];
	wire SPI_START = SPI_CTRL[1];
	wire SPI_I_MSK = SPI_CTRL[0];
	
	wire clk_divider; //Salida del divisor de reloj
	wire done;
	reg SCK_inter;
	reg load_data;
	reg en_SCK;
	wire [31:0] NEW_SPI_DATA_OUT;
	
	
	divider_clock_spi clock_divider(
		.clk_cpu(clk_cpu),
		.rst(rst),
		.en(en_SCK),
		.spi_bitrate(SPI_BITRATE),
		.SCK(clk_divider)
	);
	
	piso_sipo #(.DATA_WIDTH(32)) piso_sipo_spi(
		.clk(SCK_inter),
		.rst(rst),
		.load(load_data),
		.data_in(NEW_SPI_DATA_OUT),
		.SPI_DATA_LEN(SPI_DATA_LEN),
		.MISO(MISO),
		.done(done),
		.MOSI(MOSI),
		.data_out(SPI_DATA_IN)
	);
	
	spi_data_order #(.DATA_WIDTH(32)) data_order(
		.rst(rst),
		.en(load_data),
		.SPI_DATA_IN(SPI_DATA_OUT),
		.SPI_DATA_OUT(NEW_SPI_DATA_OUT),
		.SPI_BIT_ORDER(SPI_BIT_ORDER)
	);
	
	assign SS = done;
	
	
	always @(posedge clk_cpu or posedge rst)
	begin
	   if (rst) begin
	   	load_data = 0;
	   	SCK_inter <= 0;
	   	corrent_state <= IDLE;
	   	//SS <= 0;
	   end else begin 
	   	  corrent_state <= next_state;
	   	  //SS <= done;
	       end
	end
	
	
	assign SCK = (SPI_MODE[1] == 1'b0) ? clk_divider : ~clk_divider;
	
	always @(*) begin
		next_state = corrent_state;
		case(SPI_MODE)
			2'b00: SCK_inter <= clk_divider;
			2'b01: SCK_inter <= ~clk_divider;
			2'b10: SCK_inter <= clk_divider;
			2'b11: SCK_inter <= ~clk_divider;
			default: SCK_inter <= clk_divider;
		endcase


		//SS = 1;
		//interrpt = 0;
	   	 		
		case (corrent_state)
			IDLE: begin
			  if (SPI_ON && SPI_FRAME_START) begin
			  	next_state = LOAD;
			  	en_SCK <= 1;
			  end else begin 
			  	en_SCK <= 0;
			      end
			end
			
			LOAD: begin
			  if (SPI_START) begin
			  	load_data = 1;
			  	next_state = TRANSMIT;
			  end
			end
			
			TRANSMIT: begin
			  if (done) begin
			  	next_state = DONE;
			  end else begin 
			  	load_data = 0;
			      end
			end
			
			DONE: begin
			  //interrpt = 1;
			  next_state = IDLE;
			end
		endcase
	end
	
	
endmodule

archivos_verilog/spi_control_tb.v
module spi_control_tb;
	reg clk_cpu;
	reg rst;
	reg [31:0] SPI_BITRATE;
	reg [31:0] SPI_DATA_OUT;
	wire [31:0] SPI_DATA_IN;
	reg [8:0] SPI_CTRL;
	wire SCK;
	wire MOSI;
	reg MISO;
	wire SS;
	wire interrpt;
	
	spi_control spi_logic(
		.clk_cpu(clk_cpu),
		.rst(rst),
		.SPI_BITRATE(SPI_BITRATE),
		.SPI_DATA_OUT(SPI_DATA_OUT),
		.SPI_DATA_IN(SPI_DATA_IN),
		.SPI_CTRL(SPI_CTRL),
		.SCK(SCK),
		.MOSI(MOSI),
		.MISO(MISO),
		.SS(SS),
		.interrpt(interrpt)
	);
	
		always
		begin
			#5 clk_cpu = !clk_cpu;
		end
	
	initial 
	begin
	   clk_cpu = 1'b0;
	   //SPI_DATA_LENN = 0;
		$dumpfile("spi_controll.vcd");
		$dumpvars;
		$monitor($time, "clk_cpu=%b,rst=%b, SPI_BITRATE=%b, SPI_DATA_OUT=%b, SPI_DATA_IN=%b, SPI_CTRL=%b, SCK=%b,MOSI=%b, MISO=%b, SS=%b, interrpt=%b", clk_cpu,rst,SPI_BITRATE,SPI_DATA_OUT,SPI_DATA_IN,SPI_CTRL,SCK,MOSI,MISO,SS,interrpt);
	   
	   
	   rst = 1;
	   MISO = 0;
	   SPI_BITRATE = 2;
	   SPI_CTRL = 9'b000000000;
	   SPI_DATA_OUT = 0;

	   
	   #200;
	   rst = 0;
	   #50 SPI_CTRL = 9'b010001100;
	   #100;
	   SPI_DATA_OUT = 9;
	   SPI_CTRL = 9'b110001110;
	   //#30 //SPI_CTRL = 9'b000000000;
	   MISO = 1;
	   #50 MISO=0;
	   #50 MISO=1;
	   #50 MISO=0;
	   SPI_CTRL = 9'b110101100;
	   #1000;
	   
	   /*
	   #500 SPI_CTRL = 9'b100000110;
	   SPI_DATA_OUT = 2147483649;
	   #500 SPI_CTRL = 9'b000000100;
	   #3000;
	   */
	   //SPI_DATA_OUT = 0;
	   //SPI_CTRL = 9'b000000000;
	   //SPI_CTRL = 9'b000000000;

	   //SPI_BITRATE = 10;
	   //SPI_CTRL = 9'b011000000;
	   	$finish;
	end
	
endmodule

archivos_verilog/spi_controll.vcd
$date
	Thu Nov 21 04:47:02 2024
$end
$version
	Icarus Verilog
$end
$timescale
	1s
$end
$scope module spi_control_tb $end
$var wire 1 ! interrpt $end
$var wire 1 " SS $end
$var wire 32 # SPI_DATA_IN [31:0] $end
$var wire 1 $ SCK $end
$var wire 1 % MOSI $end
$var reg 1 & MISO $end
$var reg 32 ' SPI_BITRATE [31:0] $end
$var reg 9 ( SPI_CTRL [8:0] $end
$var reg 32 ) SPI_DATA_OUT [31:0] $end
$var reg 1 * clk_cpu $end
$var reg 1 + rst $end
$scope module spi_logic $end
$var wire 1 & MISO $end
$var wire 32 , SPI_BITRATE [31:0] $end
$var wire 9 - SPI_CTRL [8:0] $end
$var wire 32 . SPI_DATA_OUT [31:0] $end
$var wire 1 " SS $end
$var wire 1 * clk_cpu $end
$var wire 1 + rst $end
$var wire 1 / done $end
$var wire 1 0 clk_divider $end
$var wire 1 1 SPI_START $end
$var wire 1 2 SPI_ON $end
$var wire 2 3 SPI_MODE [1:0] $end
$var wire 1 4 SPI_I_MSK $end
$var wire 1 5 SPI_FRAME_START $end
$var wire 2 6 SPI_DATA_LEN [1:0] $end
$var wire 32 7 SPI_DATA_IN [31:0] $end
$var wire 1 8 SPI_BIT_ORDER $end
$var wire 1 $ SCK $end
$var wire 32 9 NEW_SPI_DATA_OUT [31:0] $end
$var wire 1 % MOSI $end
$var parameter 3 : DONE $end
$var parameter 3 ; FRAME_STOP $end
$var parameter 3 < IDLE $end
$var parameter 3 = LOAD $end
$var parameter 3 > TRANSMIT $end
$var reg 1 ? SCK_inter $end
$var reg 3 @ corrent_state [2:0] $end
$var reg 1 A en_SCK $end
$var reg 1 ! interrpt $end
$var reg 1 B load_data $end
$var reg 3 C next_state [2:0] $end
$scope module clock_divider $end
$var wire 1 * clk_cpu $end
$var wire 1 A en $end
$var wire 1 + rst $end
$var wire 32 D spi_bitrate [31:0] $end
$var reg 1 0 SCK $end
$var integer 32 E counter [31:0] $end
$upscope $end
$scope module data_order $end
$var wire 1 8 SPI_BIT_ORDER $end
$var wire 32 F SPI_DATA_IN [31:0] $end
$var wire 1 B en $end
$var wire 1 + rst $end
$var parameter 32 G DATA_WIDTH $end
$var reg 32 H SPI_DATA_OUT [31:0] $end
$var integer 32 I i [31:0] $end
$upscope $end
$scope module piso_sipo_spi $end
$var wire 1 & MISO $end
$var wire 2 J SPI_DATA_LEN [1:0] $end
$var wire 1 ? clk $end
$var wire 32 K data_in [31:0] $end
$var wire 1 B load $end
$var wire 1 + rst $end
$var parameter 32 L DATA_WIDTH $end
$var reg 1 % MOSI $end
$var reg 6 M couter_bit [5:0] $end
$var reg 5 N data_len [4:0] $end
$var reg 32 O data_out [31:0] $end
$var reg 1 / done $end
$var reg 32 P shift_reg [31:0] $end
$upscope $end
$upscope $end
$upscope $end
$enddefinitions $end
$comment Show the parameter values. $end
$dumpall
b100000 L
b100000 G
b10 >
b1 =
b0 <
b100 ;
b11 :
$end
#0
$dumpvars
b0 P
b0 O
b0 N
b100001 M
b0 K
b0 J
bx I
b0 H
b0 F
b0 E
b10 D
b0 C
0B
0A
b0 @
0?
b0 9
08
b0 7
b0 6
05
04
b0 3
02
01
00
0/
b0 .
b0 -
b10 ,
1+
0*
b0 )
b0 (
b10 '
0&
0%
0$
b0 #
0"
x!
$end
#5
1*
#10
0*
#15
1*
#20
0*
#25
1*
#30
0*
#35
1*
#40
0*
#45
1*
#50
0*
#55
1*
#60
0*
#65
1*
#70
0*
#75
1*
#80
0*
#85
1*
#90
0*
#95
1*
#100
0*
#105
1*
#110
0*
#115
1*
#120
0*
#125
1*
#130
0*
#135
1*
#140
0*
#145
1*
#150
0*
#155
1*
#160
0*
#165
1*
#170
0*
#175
1*
#180
0*
#185
1*
#190
0*
#195
1*
#200
0*
0+
#205
1*
#210
0*
#215
1*
#220
0*
#225
1*
#230
0*
#235
1*
#240
0*
#245
1*
#250
1$
b10 3
b1 6
b1 J
15
0*
b10001100 (
b10001100 -
#255
1*
#260
0*
#265
1*
#270
0*
#275
1*
#280
0*
#285
1*
#290
0*
#295
1*
#300
0*
#305
1*
#310
0*
#315
1*
#320
0*
#325
1*
#330
0*
#335
1*
#340
0*
#345
1*
#350
1A
b1 C
12
11
0*
1&
b110001110 (
b110001110 -
b1001 )
b1001 .
b1001 F
#355
b1001 P
b1001 9
b1001 H
b1001 K
b10000 N
b0 M
b10 C
1B
b1 E
b1 @
1*
#360
0*
#365
b1 M
b10011 P
1?
0$
0B
b10 @
10
b0 E
1*
#370
0*
#375
b1 E
1*
#380
0*
#385
0?
1$
00
b0 E
1*
#390
0*
#395
b1 E
1*
#400
0*
0&
#405
b10 M
b100110 P
1?
0$
10
b0 E
1*
#410
0*
#415
b1 E
1*
#420
0*
#425
0?
1$
00
b0 E
1*
#430
0*
#435
b1 E
1*
#440
0*
#445
b11 M
b1001100 P
1?
0$
10
b0 E
1*
#450
0*
1&
#455
b1 E
1*
#460
0*
#465
0?
1$
00
b0 E
1*
#470
0*
#475
b1 E
1*
#480
0*
#485
b100 M
b10011001 P
1?
0$
10
b0 E
1*
#490
0*
#495
b1 E
1*
#500
18
01
0*
b110101100 (
b110101100 -
0&
#505
0?
1$
00
b0 E
1*
#510
0*
#515
b1 E
1*
#520
0*
#525
b101 M
b100110010 P
1?
0$
10
b0 E
1*
#530
0*
#535
b1 E
1*
#540
0*
#545
0?
1$
00
b0 E
1*
#550
0*
#555
b1 E
1*
#560
0*
#565
b110 M
b1001100100 P
1?
0$
10
b0 E
1*
#570
0*
#575
b1 E
1*
#580
0*
#585
0?
1$
00
b0 E
1*
#590
0*
#595
b1 E
1*
#600
0*
#605
b111 M
b10011001000 P
1?
0$
10
b0 E
1*
#610
0*
#615
b1 E
1*
#620
0*
#625
0?
1$
00
b0 E
1*
#630
0*
#635
b1 E
1*
#640
0*
#645
b1000 M
b100110010000 P
1?
0$
10
b0 E
1*
#650
0*
#655
b1 E
1*
#660
0*
#665
0?
1$
00
b0 E
1*
#670
0*
#675
b1 E
1*
#680
0*
#685
b1001 M
b1001100100000 P
1?
0$
10
b0 E
1*
#690
0*
#695
b1 E
1*
#700
0*
#705
0?
1$
00
b0 E
1*
#710
0*
#715
b1 E
1*
#720
0*
#725
b1010 M
b10011001000000 P
1?
0$
10
b0 E
1*
#730
0*
#735
b1 E
1*
#740
0*
#745
0?
1$
00
b0 E
1*
#750
0*
#755
b1 E
1*
#760
0*
#765
b1011 M
b100110010000000 P
1?
0$
10
b0 E
1*
#770
0*
#775
b1 E
1*
#780
0*
#785
0?
1$
00
b0 E
1*
#790
0*
#795
b1 E
1*
#800
0*
#805
b1100 M
b1001100100000000 P
1?
0$
10
b0 E
1*
#810
0*
#815
b1 E
1*
#820
0*
#825
0?
1$
00
b0 E
1*
#830
0*
#835
b1 E
1*
#840
0*
#845
b1101 M
b10011001000000000 P
1%
1?
0$
10
b0 E
1*
#850
0*
#855
b1 E
1*
#860
0*
#865
0?
1$
00
b0 E
1*
#870
0*
#875
b1 E
1*
#880
0*
#885
b1110 M
b100110010000000000 P
0%
1?
0$
10
b0 E
1*
#890
0*
#895
b1 E
1*
#900
0*
#905
0?
1$
00
b0 E
1*
#910
0*
#915
b1 E
1*
#920
0*
#925
b1111 M
b1001100100000000000 P
1?
0$
10
b0 E
1*
#930
0*
#935
b1 E
1*
#940
0*
#945
0?
1$
00
b0 E
1*
#950
0*
#955
b1 E
1*
#960
0*
#965
b10000 M
b10011001000000000000 P
1%
1?
0$
10
b0 E
1*
#970
0*
#975
b1 E
1*
#980
0*
#985
0?
1$
00
b0 E
1*
#990
0*
#995
b1 E
1*
#1000
0*
#1005
b11 C
0%
1"
1/
b10011001000000000000 #
b10011001000000000000 7
b10011001000000000000 O
1?
0$
10
b0 E
1*
#1010
0*
#1015
b0 C
b1 E
b11 @
1*
#1020
0*
#1025
0?
1$
b1 C
b0 @
00
b0 E
1*
#1030
0*
#1035
b1 E
b1 @
1*
#1040
0*
#1045
1?
0$
10
b0 E
1*
#1050
0*
#1055
b1 E
1*
#1060
0*
#1065
0?
1$
00
b0 E
1*
#1070
0*
#1075
b1 E
1*
#1080
0*
#1085
1?
0$
10
b0 E
1*
#1090
0*
#1095
b1 E
1*
#1100
0*
#1105
0?
1$
00
b0 E
1*
#1110
0*
#1115
b1 E
1*
#1120
0*
#1125
1?
0$
10
b0 E
1*
#1130
0*
#1135
b1 E
1*
#1140
0*
#1145
0?
1$
00
b0 E
1*
#1150
0*
#1155
b1 E
1*
#1160
0*
#1165
1?
0$
10
b0 E
1*
#1170
0*
#1175
b1 E
1*
#1180
0*
#1185
0?
1$
00
b0 E
1*
#1190
0*
#1195
b1 E
1*
#1200
0*
#1205
1?
0$
10
b0 E
1*
#1210
0*
#1215
b1 E
1*
#1220
0*
#1225
0?
1$
00
b0 E
1*
#1230
0*
#1235
b1 E
1*
#1240
0*
#1245
1?
0$
10
b0 E
1*
#1250
0*
#1255
b1 E
1*
#1260
0*
#1265
0?
1$
00
b0 E
1*
#1270
0*
#1275
b1 E
1*
#1280
0*
#1285
1?
0$
10
b0 E
1*
#1290
0*
#1295
b1 E
1*
#1300
0*
#1305
0?
1$
00
b0 E
1*
#1310
0*
#1315
b1 E
1*
#1320
0*
#1325
1?
0$
10
b0 E
1*
#1330
0*
#1335
b1 E
1*
#1340
0*
#1345
0?
1$
00
b0 E
1*
#1350
0*
#1355
b1 E
1*
#1360
0*
#1365
1?
0$
10
b0 E
1*
#1370
0*
#1375
b1 E
1*
#1380
0*
#1385
0?
1$
00
b0 E
1*
#1390
0*
#1395
b1 E
1*
#1400
0*
#1405
1?
0$
10
b0 E
1*
#1410
0*
#1415
b1 E
1*
#1420
0*
#1425
0?
1$
00
b0 E
1*
#1430
0*
#1435
b1 E
1*
#1440
0*
#1445
1?
0$
10
b0 E
1*
#1450
0*
#1455
b1 E
1*
#1460
0*
#1465
0?
1$
00
b0 E
1*
#1470
0*
#1475
b1 E
1*
#1480
0*
#1485
1?
0$
10
b0 E
1*
#1490
0*
#1495
b1 E
1*
