archivos_verilog/logic master tb/spi_data_order.v
module spi_data_order#(
	parameter DATA_WIDTH = 32
)(
	input [1:0] SPI_DATA_LEN,
	input en,
	input rst,
	input [DATA_WIDTH-1:0] SPI_DATA_IN,
	input SPI_BIT_ORDER,
	output reg [DATA_WIDTH-1:0] SPI_DATA_OUT
);
	//Se cambia el orden de los bits segun SPI_BIT_ORDER
	
	wire [4:0] data_len;
	assign data_len = (SPI_DATA_LEN == 2'b00) ? 5'd24 :
                     (SPI_DATA_LEN == 2'b01) ? 5'd16 :
                     (SPI_DATA_LEN == 2'b10) ? 5'd8  : 5'd0;  // Para 2'b11 o cualquier otro valor	
	
	integer i;
	always @(*) 
	begin
	if (rst) begin
	i = 0;
	SPI_DATA_OUT = 0;
	end else begin
	  //if (en) begin
	   if (SPI_BIT_ORDER) begin
	   	for (i = 0; i < data_len; i = i+1) begin
	   	   SPI_DATA_OUT[i] = SPI_DATA_IN[data_len - 1 - i];
	   	end
	   end else begin
	   	SPI_DATA_OUT = SPI_DATA_IN;
	       end
	  //end 
	end
	end

endmodule

archivos_verilog/logic master/spi_logic_control.v
module spi_logic_control(
	input clk_cpu,
	input rst,
	input [31:0] SPI_DATA_OUT,
	input [8:0] SPI_CTRL,
	output SCK,
	output SS,
	output IRQ_SPI,
	
	input clk_divider, //Salida del divisor de reloj
	input done, //para identificar cuando se termina la transmision
	output SCK_inter, //SCK interno para la logica de lectura y escritura
	output reg en_SCK, //para habilitar el reloj SCK
	output reg load_data,  //para iniciar la transmision de datos
	
	output [31:0] NEW_SPI_DATA_OUT, //nuevo dato de salida modifcado segun el registro de control
	output [1:0] SPI_DATA_LEN,
	input load_data_in, //para saber cuando hacer el cambio del orden de los bits
	input [31:0] SPI_DATA_IN_I,
	output [31:0] NEW_SPI_DATA_IN //nuevo dato de entrada modifcado segun el registro de control
);

	//Parametros para los estados de la maquina
	parameter IDLE = 3'b000;
	parameter LOAD = 3'b001;
	parameter TRANSMIT = 3'b010;
	parameter LOAD_DATA = 3'b011;
	parameter DONE = 3'b100;
	
	//variables para manejar los estados
	reg [2:0] corrent_state, next_state;
	reg load_SS;
	
	//Ordenar los bit del registro SPI_CTRL
	wire SPI_ON = SPI_CTRL[8];
	wire [1:0] SPI_MODE = SPI_CTRL[7:6];
	wire SPI_BIT_ORDER = SPI_CTRL[5];
	assign SPI_DATA_LEN = SPI_CTRL[4:3];
	wire SPI_FRAME_START = SPI_CTRL[2];
	wire SPI_START = SPI_CTRL[1];
	wire SPI_I_MSK = SPI_CTRL[0];
	
	
	//reflaxion de los bist del regisrtro de salida
	spi_data_order #(.DATA_WIDTH(32)) data_order(
		.SPI_DATA_LEN(SPI_DATA_LEN),
		.en(load_data_in),
		.rst(rst),
		.SPI_DATA_IN(SPI_DATA_IN_I),
		.SPI_DATA_OUT(NEW_SPI_DATA_IN),
		.SPI_BIT_ORDER(SPI_BIT_ORDER)
	);
	
	//reflaxion de los bist del regisrtro de entrada
	spi_data_order #(.DATA_WIDTH(32)) data_order_in(
		.SPI_DATA_LEN(SPI_DATA_LEN),
		.en(load_data),
		.rst(rst),
		.SPI_DATA_IN(SPI_DATA_OUT),
		.SPI_DATA_OUT(NEW_SPI_DATA_OUT),
		.SPI_BIT_ORDER(SPI_BIT_ORDER)
	);
	
	//logica de la maquina estados
	always @(posedge clk_cpu or posedge rst)
	begin
	   if (rst) begin
	   	corrent_state <= IDLE;
	   end else begin 
	   	  corrent_state <= next_state;
	       end
	end
	
	always @(*) begin
		case (corrent_state)
			IDLE: begin
			load_data = 0;
			load_SS = 1;
			  if (SPI_ON && SPI_FRAME_START) begin
			  	en_SCK = 1;
			  	next_state = LOAD;
			  end else begin 
			  	en_SCK = 0;
			  	next_state = IDLE;
			      end
			end
			
			LOAD: begin
			en_SCK = 1;
			  if (SPI_START) begin
			  	load_data = 1;
			  	load_SS = 0;
			  	next_state = TRANSMIT;
			  end else begin
			  	load_data = 0;
			  	load_SS = 1;
			  	next_state = LOAD;
			      end
			end
			
			TRANSMIT: begin
			load_SS = 1;
			en_SCK = 1;
			load_data = 1;
			next_state = LOAD_DATA;
			end
			
			LOAD_DATA: begin
			  en_SCK = 1;
			  load_data = 1;
			  if (done) begin
			  	load_SS = 1;
			  	next_state = DONE;
			  end else begin 
			  	load_SS = 0;
			  	next_state = LOAD_DATA;
			      end
			  
			end
			
			DONE: begin
			  en_SCK = 1;
			  load_data = 0;
			  load_SS = 1;
			  next_state = IDLE;
			end
			
			default: begin
			en_SCK = 0;
			load_data = 0;
			load_SS = 1;
			next_state = IDLE;
			end
			
		endcase
	end
	
	//logica para el SCK interno el cual maneja el modulo de salida(PISO_SIPO)
	assign SCK_inter = SPI_MODE[0] ? ~clk_divider : clk_divider;
	assign SCK = SPI_MODE[1] ? ~clk_divider : clk_divider; //logica para SCK segun el modo
	assign IRQ_SPI = SPI_I_MSK ? done : 1'b0;
	assign SS = load_SS;
	
endmodule

archivos_verilog/logic master/piso_sipo.v
module piso_sipo#(
    parameter DATA_WIDTH = 32  // Ancho de los datos, configurable por el usuario
)(
    input clk,                  // Reloj del sistema
    input rst,                  // Señal de reinicio
    input load,                 // Señal para cargar nuevos datos
    input [DATA_WIDTH-1:0] data_in, // Entrada paralela de datos
    input MISO,                 // Entrada serial para recibir datos
    input [1:0] SPI_DATA_LEN,   // Configuración del ancho de datos SPI
    output reg done,            // Señal que indica cuando la operación ha terminado
    output reg MOSI,            // Salida serial para enviar datos
    output reg [DATA_WIDTH-1:0] data_out, // Salida paralela de datos recibidos
    output reg load_data_in     // Señal para cargar nuevos datos a `shift_reg`
);
   
    // Registro de desplazamiento para transmisión y recepción serial
    reg [DATA_WIDTH-1:0] shift_reg;
    reg [$clog2(DATA_WIDTH):0] couter_bit;   // Contador de bits transmitidos/recibidos
    wire [4:0] data_len;                     // Longitud de datos configurada según SPI_DATA_LEN

    // Bloque secuencial principal para manejar el envío y recepción de datos
    always @(posedge clk or posedge rst)
    begin
        if (rst) begin
            // Reset: Inicialización de registros y señales
            shift_reg <= 0;
            couter_bit <= 0;   // Inicializado fuera del rango para detener actividad
            MOSI <= 0;
            data_out <= 0;
            done <= 0;
        end else begin
            if (load) begin
		    if (couter_bit < (DATA_WIDTH - data_len)) begin
		    	/*if (couter_bit == 0) begin
		        shift_reg <= data_in;     // Cargar datos paralelos en el registro
		        //couter_bit <= 1;
		        done <= 0;
		    	end*/
		        // Envío y recepción serial:
		        MOSI <= shift_reg[0]; 			         // Enviar el bit menos significativo
		        shift_reg <= (shift_reg >> 1);                   // Desplazar bits a la derecha
		        shift_reg[(DATA_WIDTH - data_len) - 1] <= MISO;  // Recibir bit del MISO
		        couter_bit <= couter_bit + 1;                    // Incrementar el contador de bits
		        done <= 0;
		    end else begin
		        // Operación terminada:
		        data_out <= shift_reg; // Cargar el contenido recibido en la salida paralela
		        done <= 1;             // Indicar que la operación ha finalizado
		        MOSI <= 0;             // Deshabilitar la salida serial
		        //couter_bit <= 33;
            		end
            end else begin
		MOSI <= 0;
                //done <= 0;
            	shift_reg <= data_in;
            end
        end
    end
    
    
    
    // Bloque combinacional para cargar datos iniciales y configurar longitud de datos
    assign data_len = (SPI_DATA_LEN == 2'b00) ? 5'd24 :
                      (SPI_DATA_LEN == 2'b01) ? 5'd16 :
                      (SPI_DATA_LEN == 2'b10) ? 5'd8  : 5'd0;  // Para 2'b11 o cualquier otro valor
	
endmodule

archivos_verilog/divider clock/divider_clock_spi.v
module divider_clock_spi(
    input clk_cpu,           // Señal de reloj principal del CPU
    input rst,               // Señal de reinicio
    input en,                // Habilitación del divisor de reloj
    input [31:0] spi_bitrate, // Valor del bitrate deseado para SPI (controla la frecuencia del reloj SCK)
    output reg SCK           // Señal de reloj SCK generada
);

    //Se realiza un contador en cada pulso de reloj_CPU que depende del bitrate, 
    //con el fin de generar una nueva señal con una frecuencia dividida comparandola con la de la CPU,
    //esto permite que el usuario tenga control de la velocidad de transmision
	
	
    // Contador para dividir la frecuencia del reloj `clk_cpu`
    integer counter = 0;
	
    // Bloque siempre activo en el flanco positivo del reloj `clk_cpu` o al activarse `rst`
    always @(posedge clk_cpu or posedge rst) 
    begin
        if (rst) begin
            // Reinicio: Inicializar contador y señal SCK
            counter <= 0;
            SCK <= 0;
        end else begin
            if (en) begin
                // Si la habilitación está activa (`en`):
                if (counter == spi_bitrate - 1) begin
                    // Si el contador alcanza el valor deseado (basado en `spi_bitrate`):
                    counter <= 0;       // Reiniciar el contador
                    SCK <= ~SCK;        // Invertir el estado de la señal SCK (generar el siguiente flanco)
                end else begin
                    // Incrementar el contador en cada ciclo
                    counter <= counter + 1;
                end
            end else begin
                // Si no está habilitado (`en`), mantener SCK en bajo
                SCK <= 0;
            end
        end
    end
endmodule

archivos_verilog/logic master tb/spi_logic_master.v
module spi_logic_master(
	input clk_cpu,
	input rst,
	input [31:0] SPI_BITRATE,
	input [31:0] SPI_DATA_OUT,
	output [31:0] SPI_DATA_IN,
	input [8:0] SPI_CTRL,
	output SCK,
	output MOSI,
	input MISO,
	output SS,
	output IRQ_SPI
);

	//este modulo es para unir toda la parte de logica de la comunicacion SPI

	wire [31:0] NEW_SPI_DATA_OUT;
	wire clk_divider; //Salida del divisor de reloj
	wire done;
	wire SCK_inter;
	wire load_data;
	wire en_SCK;
	wire [1:0] SPI_DATA_LEN;
	
	wire load_data_in;
	wire [31:0] SPI_DATA_IN_I;
	
	
	divider_clock_spi clock_divider(
		.clk_cpu(clk_cpu),
		.rst(rst),
		.en(en_SCK),
		.spi_bitrate(SPI_BITRATE),
		.SCK(clk_divider)
	);
	
	piso_sipo #(.DATA_WIDTH(32)) piso_sipo_spi(
		.clk(SCK_inter),
		.rst(rst),
		.load(load_data),
		.data_in(NEW_SPI_DATA_OUT),
		.SPI_DATA_LEN(SPI_DATA_LEN),
		.MISO(MISO),
		.done(done),
		.MOSI(MOSI),
		.data_out(SPI_DATA_IN_I),
		.load_data_in(load_data_in)
	);
	
	spi_logic_control spi_control(
		.clk_cpu(clk_cpu),
		.rst(rst),
		.load_data(load_data),
		.SPI_DATA_OUT(SPI_DATA_OUT),
		.SPI_CTRL(SPI_CTRL),
		.SCK(SCK),
		.SS(SS),
		.IRQ_SPI(IRQ_SPI),
		.SCK_inter(SCK_inter),
		.en_SCK(en_SCK),
		.done(done),
		.SPI_DATA_LEN(SPI_DATA_LEN),
		.NEW_SPI_DATA_OUT(NEW_SPI_DATA_OUT),
		.clk_divider(clk_divider),
		.load_data_in(load_data_in),
		.SPI_DATA_IN_I(SPI_DATA_IN_I),
		.NEW_SPI_DATA_IN(SPI_DATA_IN)
	);
	
endmodule

archivos_verilog/logic master/spi_logic_master_tb.v
module spi_logic_control_tb;
	reg clk_cpu;
	reg rst;
	reg [31:0] SPI_BITRATE;
	reg [31:0] SPI_DATA_OUT;
	wire [31:0] SPI_DATA_IN;
	reg [8:0] SPI_CTRL;
	wire SCK;
	wire MOSI;
	reg MISO;
	wire SS;
	wire IRQ_SPI;
	
	spi_logic_master spi_logic(
		.clk_cpu(clk_cpu),
		.rst(rst),
		.SPI_BITRATE(SPI_BITRATE),
		.SPI_DATA_OUT(SPI_DATA_OUT),
		.SPI_DATA_IN(SPI_DATA_IN),
		.SPI_CTRL(SPI_CTRL),
		.SCK(SCK),
		.MOSI(MOSI),
		.MISO(MISO),
		.SS(SS),
		.IRQ_SPI(IRQ_SPI)
	);
	
		always
		begin
			#5 clk_cpu = !clk_cpu;
		end
	
	initial 
	begin
	   clk_cpu = 1'b0;
	   //SPI_DATA_LENN = 0;
		$dumpfile("spi_logic_masterr.vcd");
		$dumpvars;
		$monitor($time, "clk_cpu=%b,rst=%b, SPI_BITRATE=%b, SPI_DATA_OUT=%b, SPI_DATA_IN=%b, SPI_CTRL=%b, SCK=%b,MOSI=%b, MISO=%b, SS=%b, IRQ_SPI=%b", clk_cpu,rst,SPI_BITRATE,SPI_DATA_OUT,SPI_DATA_IN,SPI_CTRL,SCK,MOSI,MISO,SS,IRQ_SPI);
	   
	   
	   rst = 1;
	   MISO = 0;
	   SPI_BITRATE = 2;
	   SPI_CTRL = 9'b000000000;
	   SPI_DATA_OUT = 0;

	   
	   #100;
	   rst = 0;
	   SPI_CTRL = 9'b000001101;
	   #100;
	   SPI_CTRL = 9'b100001101;
	   #100;
	   SPI_DATA_OUT = 9;
	   SPI_CTRL = 9'b100001111;
	   //#30 //SPI_CTRL = 9'b000000000;
	   #50 MISO = 1;
	   //SPI_CTRL = 9'b100001100;
	   #50 MISO = 0;
	   #50 MISO = 1;
	   #50 MISO = 0;
	   SPI_CTRL = 9'b100001101;
	   #600;
	   SPI_DATA_OUT = 169;
	   SPI_CTRL = 9'b100101110;
	   #25 MISO = 1;
	   #30 MISO = 0;
	   #25 MISO = 1;
	   #30 MISO = 0;
	   SPI_CTRL = 9'b100101100;
	   #1000;
	   /*
	   #500 SPI_CTRL = 9'b100000110;
	   SPI_DATA_OUT = 2147483649;
	   #500 SPI_CTRL = 9'b000000100;
	   #3000;
	   */
	   //SPI_DATA_OUT = 0;
	   //SPI_CTRL = 9'b000000000;
	   //SPI_CTRL = 9'b000000000;

	   //SPI_BITRATE = 10;
	   //SPI_CTRL = 9'b011000000;
	   	$finish;
	end
endmodule

archivos_verilog/logic master/spi_logic_masterr.vcd
$date
	Fri May 30 22:26:13 2025
$end
$version
	Icarus Verilog
$end
$timescale
	1s
$end
$scope module spi_logic_control_tb $end
$var wire 1 ! SS $end
$var wire 32 " SPI_DATA_IN [31:0] $end
$var wire 1 # SCK $end
$var wire 1 $ MOSI $end
$var wire 1 % IRQ_SPI $end
$var reg 1 & MISO $end
$var reg 32 ' SPI_BITRATE [31:0] $end
$var reg 9 ( SPI_CTRL [8:0] $end
$var reg 32 ) SPI_DATA_OUT [31:0] $end
$var reg 1 * clk_cpu $end
$var reg 1 + rst $end
$scope module spi_logic $end
$var wire 1 & MISO $end
$var wire 32 , SPI_BITRATE [31:0] $end
$var wire 9 - SPI_CTRL [8:0] $end
$var wire 32 . SPI_DATA_OUT [31:0] $end
$var wire 1 * clk_cpu $end
$var wire 1 + rst $end
$var wire 1 / load_data_in $end
$var wire 1 0 load_data $end
$var wire 1 1 en_SCK $end
$var wire 1 2 done $end
$var wire 1 3 clk_divider $end
$var wire 1 ! SS $end
$var wire 2 4 SPI_DATA_LEN [1:0] $end
$var wire 32 5 SPI_DATA_IN_I [31:0] $end
$var wire 32 6 SPI_DATA_IN [31:0] $end
$var wire 1 7 SCK_inter $end
$var wire 1 # SCK $end
$var wire 32 8 NEW_SPI_DATA_OUT [31:0] $end
$var wire 1 $ MOSI $end
$var wire 1 % IRQ_SPI $end
$scope module clock_divider $end
$var wire 1 * clk_cpu $end
$var wire 1 + rst $end
$var wire 32 9 spi_bitrate [31:0] $end
$var wire 1 1 en $end
$var reg 1 3 SCK $end
$var reg 32 : counter [31:0] $end
$upscope $end
$scope module piso_sipo_spi $end
$var wire 1 & MISO $end
$var wire 1 + rst $end
$var wire 1 0 load $end
$var wire 5 ; data_len [4:0] $end
$var wire 32 < data_in [31:0] $end
$var wire 1 7 clk $end
$var wire 2 = SPI_DATA_LEN [1:0] $end
$var parameter 32 > DATA_WIDTH $end
$var reg 1 $ MOSI $end
$var reg 6 ? couter_bit [5:0] $end
$var reg 32 @ data_out [31:0] $end
$var reg 1 2 done $end
$var reg 1 / load_data_in $end
$var reg 32 A shift_reg [31:0] $end
$upscope $end
$scope module spi_control $end
$var wire 9 B SPI_CTRL [8:0] $end
$var wire 32 C SPI_DATA_IN_I [31:0] $end
$var wire 32 D SPI_DATA_OUT [31:0] $end
$var wire 1 ! SS $end
$var wire 1 * clk_cpu $end
$var wire 1 3 clk_divider $end
$var wire 1 2 done $end
$var wire 1 / load_data_in $end
$var wire 1 + rst $end
$var wire 1 E SPI_START $end
$var wire 1 F SPI_ON $end
$var wire 2 G SPI_MODE [1:0] $end
$var wire 1 H SPI_I_MSK $end
$var wire 1 I SPI_FRAME_START $end
$var wire 2 J SPI_DATA_LEN [1:0] $end
$var wire 1 K SPI_BIT_ORDER $end
$var wire 1 7 SCK_inter $end
$var wire 1 # SCK $end
$var wire 32 L NEW_SPI_DATA_OUT [31:0] $end
$var wire 32 M NEW_SPI_DATA_IN [31:0] $end
$var wire 1 % IRQ_SPI $end
$var parameter 3 N DONE $end
$var parameter 3 O IDLE $end
$var parameter 3 P LOAD $end
$var parameter 3 Q LOAD_DATA $end
$var parameter 3 R TRANSMIT $end
$var reg 3 S corrent_state [2:0] $end
$var reg 1 1 en_SCK $end
$var reg 1 T load_SS $end
$var reg 1 0 load_data $end
$var reg 3 U next_state [2:0] $end
$scope module data_order $end
$var wire 1 K SPI_BIT_ORDER $end
$var wire 32 V SPI_DATA_IN [31:0] $end
$var wire 2 W SPI_DATA_LEN [1:0] $end
$var wire 1 / en $end
$var wire 1 + rst $end
$var wire 5 X data_len [4:0] $end
$var parameter 32 Y DATA_WIDTH $end
$var reg 32 Z SPI_DATA_OUT [31:0] $end
$var integer 32 [ i [31:0] $end
$upscope $end
$scope module data_order_in $end
$var wire 1 K SPI_BIT_ORDER $end
$var wire 32 \ SPI_DATA_IN [31:0] $end
$var wire 2 ] SPI_DATA_LEN [1:0] $end
$var wire 1 0 en $end
$var wire 1 + rst $end
$var wire 5 ^ data_len [4:0] $end
$var parameter 32 _ DATA_WIDTH $end
$var reg 32 ` SPI_DATA_OUT [31:0] $end
$var integer 32 a i [31:0] $end
$upscope $end
$upscope $end
$upscope $end
$upscope $end
$enddefinitions $end
$comment Show the parameter values. $end
$dumpall
b100000 _
b100000 Y
b10 R
b11 Q
b1 P
b0 O
b100 N
b100000 >
$end
#0
$dumpvars
b0 a
b0 `
b11000 ^
b0 ]
b0 \
b0 [
b0 Z
b11000 X
b0 W
b0 V
b0 U
1T
b0 S
b0 M
b0 L
0K
b0 J
0I
0H
b0 G
0F
0E
b0 D
b0 C
b0 B
b0 A
b0 @
b0 ?
b0 =
b0 <
b11000 ;
b0 :
b10 9
b0 8
07
b0 6
b0 5
b0 4
03
02
01
00
x/
b0 .
b0 -
b10 ,
1+
0*
b0 )
b0 (
b10 '
0&
0%
0$
0#
b0 "
1!
$end
#5
1*
#10
0*
#15
1*
#20
0*
#25
1*
#30
0*
#35
1*
#40
0*
#45
1*
#50
0*
#55
1*
#60
0*
#65
1*
#70
0*
#75
1*
#80
0*
#85
1*
#90
0*
#95
1*
#100
b10000 X
b10000 ^
b10000 ;
b1 4
b1 =
b1 J
b1 W
b1 ]
1I
1H
0*
b1101 (
b1101 -
b1101 B
0+
#105
1*
#110
0*
#115
1*
#120
0*
#125
1*
#130
0*
#135
1*
#140
0*
#145
1*
#150
0*
#155
1*
#160
0*
#165
1*
#170
0*
#175
1*
#180
0*
#185
1*
#190
0*
#195
1*
#200
b1 U
11
1F
0*
b100001101 (
b100001101 -
b100001101 B
#205
b1 S
b1 :
1*
#210
0*
#215
17
1#
13
b0 :
1*
#220
0*
#225
b1 :
1*
#230
0*
#235
07
0#
03
b0 :
1*
#240
0*
#245
b1 :
1*
#250
0*
#255
17
1#
13
b0 :
1*
#260
0*
#265
b1 :
1*
#270
0*
#275
07
0#
03
b0 :
1*
#280
0*
#285
b1 :
1*
#290
0*
#295
17
1#
13
b0 :
1*
#300
b10 U
0!
0T
10
1E
b1001 8
b1001 <
b1001 L
b1001 `
0*
b100001111 (
b100001111 -
b100001111 B
b1001 )
b1001 .
b1001 D
b1001 \
#305
b11 U
1!
1T
b10 S
b1 :
1*
#310
0*
#315
07
0#
0!
0T
03
b0 :
b11 S
1*
#320
0*
#325
b1 :
1*
#330
0*
#335
b1 ?
17
1#
13
b0 :
1*
#340
0*
#345
b1 :
1*
#350
0*
1&
#355
07
0#
03
b0 :
1*
#360
0*
#365
b1 :
1*
#370
0*
#375
b10 ?
b1000000000000000 A
17
1#
13
b0 :
1*
#380
0*
#385
b1 :
1*
#390
0*
#395
07
0#
03
b0 :
1*
#400
0*
0&
#405
b1 :
1*
#410
0*
#415
b11 ?
b100000000000000 A
17
1#
13
b0 :
1*
#420
0*
#425
b1 :
1*
#430
0*
#435
07
0#
03
b0 :
1*
#440
0*
#445
b1 :
1*
#450
0*
1&
#455
b100 ?
b1010000000000000 A
17
1#
13
b0 :
1*
#460
0*
#465
b1 :
1*
#470
0*
#475
07
0#
03
b0 :
1*
#480
0*
#485
b1 :
1*
#490
0*
#495
b101 ?
b1101000000000000 A
17
1#
13
b0 :
1*
#500
0E
0*
b100001101 (
b100001101 -
b100001101 B
0&
#505
b1 :
1*
#510
0*
#515
07
0#
03
b0 :
1*
#520
0*
#525
b1 :
1*
#530
0*
#535
b110 ?
b110100000000000 A
17
1#
13
b0 :
1*
#540
0*
#545
b1 :
1*
#550
0*
#555
07
0#
03
b0 :
1*
#560
0*
#565
b1 :
1*
#570
0*
#575
b111 ?
b11010000000000 A
17
1#
13
b0 :
1*
#580
0*
#585
b1 :
1*
#590
0*
#595
07
0#
03
b0 :
1*
#600
0*
#605
b1 :
1*
#610
0*
#615
b1000 ?
b1101000000000 A
17
1#
13
b0 :
1*
#620
0*
#625
b1 :
1*
#630
0*
#635
07
0#
03
b0 :
1*
#640
0*
#645
b1 :
1*
#650
0*
#655
b1001 ?
b110100000000 A
17
1#
13
b0 :
1*
#660
0*
#665
b1 :
1*
#670
0*
#675
07
0#
03
b0 :
1*
#680
0*
#685
b1 :
1*
#690
0*
#695
b1010 ?
b11010000000 A
17
1#
13
b0 :
1*
#700
0*
#705
b1 :
1*
#710
0*
#715
07
0#
03
b0 :
1*
#720
0*
#725
b1 :
1*
#730
0*
#735
b1011 ?
b1101000000 A
17
1#
13
b0 :
1*
#740
0*
#745
b1 :
1*
#750
0*
#755
07
0#
03
b0 :
1*
#760
0*
#765
b1 :
1*
#770
0*
#775
b1100 ?
b110100000 A
17
1#
13
b0 :
1*
#780
0*
#785
b1 :
1*
#790
0*
#795
07
0#
03
b0 :
1*
#800
0*
#805
b1 :
1*
#810
0*
#815
b1101 ?
b11010000 A
17
1#
13
b0 :
1*
#820
0*
#825
b1 :
1*
#830
0*
#835
07
0#
03
b0 :
1*
#840
0*
#845
b1 :
1*
#850
0*
#855
b1110 ?
b1101000 A
17
1#
13
b0 :
1*
#860
0*
#865
b1 :
1*
#870
0*
#875
07
0#
03
b0 :
1*
#880
0*
#885
b1 :
1*
#890
0*
#895
b1111 ?
b110100 A
17
1#
13
b0 :
1*
#900
0*
#905
b1 :
1*
#910
0*
#915
07
0#
03
b0 :
1*
#920
0*
#925
b1 :
1*
#930
0*
#935
b10000 ?
b11010 A
17
1#
13
b0 :
1*
#940
0*
#945
b1 :
1*
#950
0*
#955
07
0#
03
b0 :
1*
#960
0*
#965
b1 :
1*
#970
0*
#975
b100 U
1!
1T
1%
b11010 "
b11010 6
b11010 M
b11010 Z
12
b11010 5
b11010 @
b11010 C
b11010 V
17
1#
13
b0 :
1*
#980
0*
#985
b0 U
00
b100 S
b1 :
1*
#990
0*
#995
07
0#
b1 U
03
b0 :
b0 S
1*
#1000
0*
#1005
b1 S
b1 :
1*
#1010
0*
#1015
b1001 A
17
1#
13
b0 :
1*
#1020
0*
#1025
b1 :
1*
#1030
0*
#1035
07
0#
03
b0 :
1*
#1040
0*
#1045
b1 :
1*
#1050
0*
#1055
17
1#
13
b0 :
1*
#1060
0*
#1065
b1 :
1*
#1070
0*
#1075
07
0#
03
b0 :
1*
#1080
0*
#1085
b1 :
1*
#1090
0*
#1095
17
1#
13
b0 :
1*
#1100
b101100000000000 "
b101100000000000 6
b101100000000000 M
b101100000000000 Z
b10000 [
b10000 a
b10 U
0!
0T
10
0%
1K
1E
0H
b1001010100000000 8
b1001010100000000 <
b1001010100000000 L
b1001010100000000 `
0*
b100101110 (
b100101110 -
b100101110 B
b10101001 )
b10101001 .
b10101001 D
b10101001 \
#1105
b11 U
1!
1T
b10 S
b1 :
1*
#1110
0*
#1115
07
0#
b100 U
03
b0 :
b11 S
1*
#1120
0*
#1125
b0 U
00
b100 S
b1 :
1*
1&
#1130
0*
#1135
b1001010100000000 A
17
1#
b1 U
13
b0 :
b0 S
1*
#1140
0*
#1145
b10 U
0!
0T
10
b1 S
b1 :
1*
#1150
0*
#1155
07
0#
b11 U
1!
1T
03
b0 :
b10 S
1*
0&
#1160
0*
#1165
b100 U
b11 S
b1 :
1*
#1170
0*
#1175
17
1#
b0 U
00
13
b0 :
b100 S
1*
#1180
0*
1&
#1185
b1 U
b0 S
b1 :
1*
#1190
0*
#1195
07
0#
b10 U
0!
0T
10
03
b0 :
b1 S
1*
#1200
0*
#1205
b11 U
1!
1T
b10 S
b1 :
1*
#1210
0E
0*
b100101100 (
b100101100 -
b100101100 B
0&
#1215
b10101001 "
b10101001 6
b10101001 M
b10101001 Z
b10000 [
b1001010100000000 5
b1001010100000000 @
b1001010100000000 C
b1001010100000000 V
17
1#
b100 U
13
b0 :
b11 S
1*
#1220
0*
#1225
b0 U
00
b100 S
b1 :
1*
#1230
0*
#1235
07
0#
b1 U
03
b0 :
b0 S
1*
#1240
0*
#1245
b1 S
b1 :
1*
#1250
0*
#1255
17
1#
13
b0 :
1*
#1260
0*
#1265
b1 :
1*
#1270
0*
#1275
07
0#
03
b0 :
1*
#1280
0*
#1285
b1 :
1*
#1290
0*
#1295
17
1#
13
b0 :
1*
#1300
0*
#1305
b1 :
1*
#1310
0*
#1315
07
0#
03
b0 :
1*
#1320
0*
#1325
b1 :
1*
#1330
0*
#1335
17
1#
13
b0 :
1*
#1340
0*
#1345
b1 :
1*
#1350
0*
#1355
07
0#
03
b0 :
1*
#1360
0*
#1365
b1 :
1*
#1370
0*
#1375
17
1#
13
b0 :
1*
#1380
0*
#1385
b1 :
1*
#1390
0*
#1395
07
0#
03
b0 :
1*
#1400
0*
#1405
b1 :
1*
#1410
0*
#1415
17
1#
13
b0 :
1*
#1420
0*
#1425
b1 :
1*
#1430
0*
#1435
07
0#
03
b0 :
1*
#1440
0*
#1445
b1 :
1*
#1450
0*
#1455
17
1#
13
b0 :
1*
#1460
0*
#1465
b1 :
1*
#1470
0*
#1475
07
0#
03
b0 :
1*
#1480
0*
#1485
b1 :
1*
#1490
0*
#1495
17
1#
13
b0 :
1*
#1500
0*
#1505
b1 :
1*
#1510
0*
#1515
07
0#
03
b0 :
1*
#1520
0*
#1525
b1 :
1*
#1530
0*
#1535
17
1#
13
b0 :
1*
#1540
0*
#1545
b1 :
1*
#1550
0*
#1555
07
0#
03
b0 :
1*
#1560
0*
#1565
b1 :
1*
#1570
0*
#1575
17
1#
13
b0 :
1*
#1580
0*
#1585
b1 :
1*
#1590
0*
#1595
07
0#
03
b0 :
1*
#1600
0*
#1605
b1 :
1*
#1610
0*
#1615
17
1#
13
b0 :
1*
#1620
0*
#1625
b1 :
1*
#1630
0*
#1635
07
0#
03
b0 :
1*
#1640
0*
#1645
b1 :
1*
#1650
0*
#1655
17
1#
13
b0 :
1*
#1660
0*
#1665
b1 :
1*
#1670
0*
#1675
07
0#
03
b0 :
1*
#1680
0*
#1685
b1 :
1*
#1690
0*
#1695
17
1#
13
b0 :
1*
#1700
0*
#1705
b1 :
1*
#1710
0*
#1715
07
0#
03
b0 :
1*
#1720
0*
#1725
b1 :
1*
#1730
0*
#1735
17
1#
13
b0 :
1*
#1740
0*
#1745
b1 :
1*
#1750
0*
#1755
07
0#
03
b0 :
1*
#1760
0*
#1765
b1 :
1*
#1770
0*
#1775
17
1#
13
b0 :
1*
#1780
0*
#1785
b1 :
1*
#1790
0*
#1795
07
0#
03
b0 :
1*
#1800
0*
#1805
b1 :
1*
#1810
0*
#1815
17
1#
13
b0 :
1*
#1820
0*
#1825
b1 :
1*
#1830
0*
#1835
07
0#
03
b0 :
1*
#1840
0*
#1845
b1 :
1*
#1850
0*
#1855
17
1#
13
b0 :
1*
#1860
0*
#1865
b1 :
1*
#1870
0*
#1875
07
0#
03
b0 :
1*
#1880
0*
#1885
b1 :
1*
#1890
0*
#1895
17
1#
13
b0 :
1*
#1900
0*
#1905
b1 :
1*
#1910
0*
#1915
07
0#
03
b0 :
1*
#1920
0*
#1925
b1 :
1*
#1930
0*
#1935
17
1#
13
b0 :
1*
#1940
0*
#1945
b1 :
1*
#1950
0*
#1955
07
0#
03
b0 :
1*
#1960
0*
#1965
b1 :
1*
#1970
0*
#1975
17
1#
13
b0 :
1*
#1980
0*
#1985
b1 :
1*
#1990
0*
#1995
07
0#
03
b0 :
1*
#2000
0*
#2005
b1 :
1*
#2010
0*
#2015
17
1#
13
b0 :
1*
#2020
0*
#2025
b1 :
1*
#2030
0*
#2035
07
0#
03
b0 :
1*
#2040
0*
#2045
b1 :
1*
#2050
0*
#2055
17
1#
13
b0 :
1*
#2060
0*
#2065
b1 :
1*
#2070
0*
#2075
07
0#
03
b0 :
1*
#2080
0*
#2085
b1 :
1*
#2090
0*
#2095
17
1#
13
b0 :
1*
#2100
0*
#2105
b1 :
1*
#2110
0*
#2115
07
0#
03
b0 :
1*
#2120
0*
#2125
b1 :
1*
#2130
0*
#2135
17
1#
13
b0 :
1*
#2140
0*
#2145
b1 :
1*
#2150
0*
#2155
07
0#
03
b0 :
1*
#2160
0*
#2165
b1 :
1*
#2170
0*
#2175
17
1#
13
b0 :
1*
#2180
0*
#2185
b1 :
1*
#2190
0*
#2195
07
0#
03
b0 :
1*
#2200
0*
#2205
b1 :
1*
