archivos_verilog/piso sipo/piso_sipo.v
module piso_sipo#(
    parameter DATA_WIDTH = 32  // Ancho de los datos, configurable por el usuario
)(
    input clk,                  // Reloj del sistema
    input rst,                  // Señal de reinicio
    input load,                 // Señal para cargar nuevos datos
    input [DATA_WIDTH-1:0] data_in, // Entrada paralela de datos
    input MISO,                 // Entrada serial para recibir datos
    input [1:0] SPI_DATA_LEN,   // Configuración del ancho de datos SPI
    output reg done,            // Señal que indica cuando la operación ha terminado
    output reg MOSI,            // Salida serial para enviar datos
    output reg [DATA_WIDTH-1:0] data_out, // Salida paralela de datos recibidos
    output reg load_data_in     // Señal para cargar nuevos datos a `shift_reg`
);

    // Registro de desplazamiento para transmisión y recepción serial
    reg [DATA_WIDTH-1:0] shift_reg;
    reg [$clog2(DATA_WIDTH):0] couter_bit;  // Contador de bits transmitidos/recibidos
    reg [4:0] data_len;                     // Longitud de datos configurada según SPI_DATA_LEN

    // Bloque secuencial principal para manejar el envío y recepción de datos
    always @(posedge clk or posedge rst)
    begin
        if (rst) begin
            // Reset: Inicialización de registros y señales
            shift_reg <= 0;
            couter_bit <= 33;   // Inicializado fuera del rango para detener actividad
            MOSI <= 0;
            data_out <= 0;
            done <= 0;
            data_len <= 0;
            load_data_in <= 0;
        end else begin
            if (couter_bit < (DATA_WIDTH - data_len)) begin
                // Envío y recepción serial:
                MOSI <= shift_reg[(DATA_WIDTH - data_len) - 1]; // Enviar el bit más significativo
                shift_reg <= shift_reg << 1;                   // Desplazar bits a la izquierda
                shift_reg[0] <= MISO;                          // Recibir bit del MISO
                couter_bit <= couter_bit + 1;                  // Incrementar el contador de bits
                load_data_in <= 0;                             // Asegurar que no se recargue `shift_reg`
            end else begin
                // Operación terminada:
                data_out <= shift_reg; // Cargar el contenido recibido en la salida paralela
                done <= 1;             // Indicar que la operación ha finalizado
                MOSI <= 0;             // Deshabilitar la salida serial
                load_data_in <= 1;     // Señal para permitir la recarga de datos
            end
        end
    end

    // Bloque combinacional para cargar datos iniciales y configurar longitud de datos
    always @(*) begin
        if (load) begin
            // Si se activa `load`, cargar los nuevos datos y reiniciar el contador:
            shift_reg = data_in;     // Cargar datos paralelos en el registro
            couter_bit = 0;          // Reiniciar el contador
            MOSI = 0;                // Inicializar salida serial
            done = 0;                // Reiniciar señal de operación terminada
            case (SPI_DATA_LEN)       // Configuración de longitud de datos:
                2'b00: data_len = 24; // 24 bits
                2'b01: data_len = 16; // 16 bits
                2'b10: data_len = 8;  // 8 bits
                2'b11: data_len = 0;  // Completa longitud de 32 bits
                default: data_len = 0;
            endcase
        end 
    end

endmodule

archivos_verilog/piso sipo/piso_sipo_tb.v
module piso_sipo_tb;
	reg clk;
	reg rst;
	reg load;
	reg [15:0] data_in;
	reg [1:0] SPI_DATA_LEN;
	reg MISO;
	wire done;
	wire MOSI;
	wire [15:0]data_out;
	wire load_data_in;
	
	piso_sipo #(.DATA_WIDTH(16)) uut_piso_spi(
		.clk(clk),
		.rst(rst),
		.load(load),
		.data_in(data_in),
		.SPI_DATA_LEN(SPI_DATA_LEN),
		.MISO(MISO),
		.done(done),
		.MOSI(MOSI),
		.data_out(data_out),
		.load_data_in(load_data_in)
	);
	
	always
		begin
			#5 clk = !clk;
		end
	
	initial 
	begin
	   clk=0;
		$dumpfile("piso_sipoo.vcd");
		$dumpvars;
		$monitor($time, "clk=%b,rst=%b,load=%b, data_in=%b, SPI_DATA_LEN=%b, MISO=%b, done=%b, MOSI=%b, data_out=%b, load_data_in=%b",
			clk,rst,load,data_in,SPI_DATA_LEN,MISO,done,MOSI,data_out,load_data_in);
	   rst=1;
	   load=0;
	   data_in=16'b0;
	   MISO=0;
	   SPI_DATA_LEN = 2'b00;
	   
	   #20 rst=0;
	   SPI_DATA_LEN = 2'b01;
	   //load=1; 
	   data_in=16'b0010010011111111;
	   #20 MISO = 1;
	   #20 MISO=0;
	   #20 MISO=1;
	   #20 MISO=0;
	   
	   #200 load=1;
	   #10 load=0;
	   //wait(done);
	   
	   data_in=16'b1010101010101010;
	   #200 load=1;
	   #10 load=0;
	   #100;
	   
	   $finish;
	   
	end
	
	
endmodule

archivos_verilog/piso sipo/piso_sipoo.vcd
$date
	Thu Apr 24 21:04:10 2025
$end
$version
	Icarus Verilog
$end
$timescale
	1s
$end
$scope module piso_sipo_tb $end
$var wire 1 ! load_data_in $end
$var wire 1 " done $end
$var wire 16 # data_out [15:0] $end
$var wire 1 $ MOSI $end
$var reg 1 % MISO $end
$var reg 2 & SPI_DATA_LEN [1:0] $end
$var reg 1 ' clk $end
$var reg 16 ( data_in [15:0] $end
$var reg 1 ) load $end
$var reg 1 * rst $end
$scope module uut_piso_spi $end
$var wire 1 % MISO $end
$var wire 2 + SPI_DATA_LEN [1:0] $end
$var wire 1 ' clk $end
$var wire 16 , data_in [15:0] $end
$var wire 1 ) load $end
$var wire 1 * rst $end
$var parameter 32 - DATA_WIDTH $end
$var reg 1 $ MOSI $end
$var reg 5 . couter_bit [4:0] $end
$var reg 5 / data_len [4:0] $end
$var reg 16 0 data_out [15:0] $end
$var reg 1 " done $end
$var reg 1 ! load_data_in $end
$var reg 16 1 shift_reg [15:0] $end
$upscope $end
$upscope $end
$enddefinitions $end
$comment Show the parameter values. $end
$dumpall
b10000 -
$end
#0
$dumpvars
b0 1
b0 0
b0 /
b1 .
b0 ,
b0 +
1*
0)
b0 (
0'
b0 &
0%
0$
b0 #
0"
0!
$end
#5
1'
#10
0'
#15
1'
#20
0'
b10010011111111 (
b10010011111111 ,
b1 &
b1 +
0*
#25
b10 .
1'
#30
0'
#35
b11 .
1'
#40
0'
1%
#45
b100 .
b1 1
1'
#50
0'
#55
b101 .
b11 1
1'
#60
0'
0%
#65
b110 .
b110 1
1'
#70
0'
#75
b111 .
b1100 1
1'
#80
0'
1%
#85
b1000 .
b11001 1
1'
#90
0'
#95
b1001 .
b110011 1
1'
#100
0'
0%
#105
b1010 .
b1100110 1
1'
#110
0'
#115
b1011 .
b11001100 1
1'
#120
0'
#125
b1100 .
b110011000 1
1'
#130
0'
#135
b1101 .
b1100110000 1
1'
#140
0'
#145
b1110 .
b11001100000 1
1'
#150
0'
#155
b1111 .
b110011000000 1
1'
#160
0'
#165
b10000 .
b1100110000000 1
1'
#170
0'
#175
1!
1"
b1100110000000 #
b1100110000000 0
1'
#180
0'
#185
1'
#190
0'
#195
1'
#200
0'
#205
1'
#210
0'
#215
1'
#220
0'
#225
1'
#230
0'
#235
1'
#240
0'
#245
1'
#250
0'
#255
1'
#260
0'
#265
1'
#270
0'
#275
1'
#280
0'
#285
1'
#290
0'
#295
1'
#300
b10000 /
0"
b0 .
b10010011111111 1
0'
1)
#305
1"
b10010011111111 #
b10010011111111 0
1'
#310
0'
b1010101010101010 (
b1010101010101010 ,
0)
#315
1'
#320
0'
#325
1'
#330
0'
#335
1'
#340
0'
#345
1'
#350
0'
#355
1'
#360
0'
#365
1'
#370
0'
#375
1'
#380
0'
#385
1'
#390
0'
#395
1'
#400
0'
#405
1'
#410
0'
#415
1'
#420
0'
#425
1'
#430
0'
#435
1'
#440
0'
#445
1'
#450
0'
#455
1'
#460
0'
#465
1'
#470
0'
#475
1'
#480
0'
#485
1'
#490
0'
#495
1'
#500
0'
#505
1'
#510
0"
b1010101010101010 1
0'
1)
#515
1"
b1010101010101010 #
b1010101010101010 0
1'
#520
0'
0)
