archivos_verilog/divider clock/divider_clock_spi.v
module divider_clock_spi(
    input clk_cpu,           // Señal de reloj principal del CPU
    input rst,               // Señal de reinicio
    input en,                // Habilitación del divisor de reloj
    input [31:0] spi_bitrate, // Valor del bitrate deseado para SPI (controla la frecuencia del reloj SCK)
    output reg SCK           // Señal de reloj SCK generada
);

    //Se realiza un contador en cada pulso de reloj_CPU que depende del bitrate, 
    //con el fin de generar una nueva señal con una frecuencia dividida comparandola con la de la CPU,
    //esto permite que el usuario tenga control de la velocidad de transmision
	
	
    // Contador para dividir la frecuencia del reloj `clk_cpu`
    integer counter = 0;
	
    // Bloque siempre activo en el flanco positivo del reloj `clk_cpu` o al activarse `rst`
    always @(posedge clk_cpu or posedge rst) 
    begin
        if (rst) begin
            // Reinicio: Inicializar contador y señal SCK
            counter <= 0;
            SCK <= 0;
        end else begin
            if (en) begin
                // Si la habilitación está activa (`en`):
                if (counter == spi_bitrate - 1) begin
                    // Si el contador alcanza el valor deseado (basado en `spi_bitrate`):
                    counter <= 0;       // Reiniciar el contador
                    SCK <= ~SCK;        // Invertir el estado de la señal SCK (generar el siguiente flanco)
                end else begin
                    // Incrementar el contador en cada ciclo
                    counter <= counter + 1;
                end
            end else begin
                // Si no está habilitado (`en`), mantener SCK en bajo
                SCK <= 0;
            end
        end
    end
endmodule

archivos_verilog/divider clock/divider_clock_spi_tb.v
`timescale 1ns / 1ps
module divider_clock_spi_tb;

	reg clk_cpu;
	reg rst;
	reg [31:0] spi_bitrate;
	reg en;
	wire SCK;
	
	divider_clock_spi uut_divider_spi(
	    .clk_cpu(clk_cpu),
	    .rst(rst),
	    .spi_bitrate(spi_bitrate),
	    .en(en),
	    .SCK(SCK)
	);
	
	always
		begin
			#5 clk_cpu = !clk_cpu;
		end
	
	initial 
	begin
	   clk_cpu = 1'b0;
	 
		$dumpfile("divider_clock_spii.vcd");
		$dumpvars;
		$monitor($time, "clk_cpu=%b,rst=%b, spi_bitrate=%b, en=%b, SCK=%b", clk_cpu,rst,spi_bitrate,en,SCK);
	   
	   
	   rst = 1;
	   en = 0;
	   spi_bitrate = 6;
	   
	   #20;
	   en = 1;
	   rst = 0;
	   
	   #500;
	   
	   spi_bitrate = 12;
	   #500;
	   
	   	$finish;
	end
endmodule

archivos_verilog/divider clock/divider_clock_spii.vcd
$date
	Thu Apr 24 19:46:45 2025
$end
$version
	Icarus Verilog
$end
$timescale
	1ps
$end
$scope module divider_clock_spi_tb $end
$var wire 1 ! SCK $end
$var reg 1 " clk_cpu $end
$var reg 1 # en $end
$var reg 1 $ rst $end
$var reg 32 % spi_bitrate [31:0] $end
$scope module uut_divider_spi $end
$var wire 1 " clk_cpu $end
$var wire 1 # en $end
$var wire 1 $ rst $end
$var wire 32 & spi_bitrate [31:0] $end
$var reg 1 ! SCK $end
$var integer 32 ' counter [31:0] $end
$upscope $end
$upscope $end
$enddefinitions $end
$comment Show the parameter values. $end
$dumpall
$end
#0
$dumpvars
b0 '
b110 &
b110 %
1$
0#
0"
0!
$end
#5000
1"
#10000
0"
#15000
1"
#20000
0"
0$
1#
#25000
b1 '
1"
#30000
0"
#35000
b10 '
1"
#40000
0"
#45000
b11 '
1"
#50000
0"
#55000
b100 '
1"
#60000
0"
#65000
b101 '
1"
#70000
0"
#75000
1!
b0 '
1"
#80000
0"
#85000
b1 '
1"
#90000
0"
#95000
b10 '
1"
#100000
0"
#105000
b11 '
1"
#110000
0"
#115000
b100 '
1"
#120000
0"
#125000
b101 '
1"
#130000
0"
#135000
0!
b0 '
1"
#140000
0"
#145000
b1 '
1"
#150000
0"
#155000
b10 '
1"
#160000
0"
#165000
b11 '
1"
#170000
0"
#175000
b100 '
1"
#180000
0"
#185000
b101 '
1"
#190000
0"
#195000
1!
b0 '
1"
#200000
0"
#205000
b1 '
1"
#210000
0"
#215000
b10 '
1"
#220000
0"
#225000
b11 '
1"
#230000
0"
#235000
b100 '
1"
#240000
0"
#245000
b101 '
1"
#250000
0"
#255000
0!
b0 '
1"
#260000
0"
#265000
b1 '
1"
#270000
0"
#275000
b10 '
1"
#280000
0"
#285000
b11 '
1"
#290000
0"
#295000
b100 '
1"
#300000
0"
#305000
b101 '
1"
#310000
0"
#315000
1!
b0 '
1"
#320000
0"
#325000
b1 '
1"
#330000
0"
#335000
b10 '
1"
#340000
0"
#345000
b11 '
1"
#350000
0"
#355000
b100 '
1"
#360000
0"
#365000
b101 '
1"
#370000
0"
#375000
0!
b0 '
1"
#380000
0"
#385000
b1 '
1"
#390000
0"
#395000
b10 '
1"
#400000
0"
#405000
b11 '
1"
#410000
0"
#415000
b100 '
1"
#420000
0"
#425000
b101 '
1"
#430000
0"
#435000
1!
b0 '
1"
#440000
0"
#445000
b1 '
1"
#450000
0"
#455000
b10 '
1"
#460000
0"
#465000
b11 '
1"
#470000
0"
#475000
b100 '
1"
#480000
0"
#485000
b101 '
1"
#490000
0"
#495000
0!
b0 '
1"
#500000
0"
#505000
b1 '
1"
#510000
0"
#515000
b10 '
1"
#520000
0"
b1100 %
b1100 &
#525000
b11 '
1"
#530000
0"
#535000
b100 '
1"
#540000
0"
#545000
b101 '
1"
#550000
0"
#555000
b110 '
1"
#560000
0"
#565000
b111 '
1"
#570000
0"
#575000
b1000 '
1"
#580000
0"
#585000
b1001 '
1"
#590000
0"
#595000
b1010 '
1"
#600000
0"
#605000
b1011 '
1"
#610000
0"
#615000
1!
b0 '
1"
#620000
0"
#625000
b1 '
1"
#630000
0"
#635000
b10 '
1"
#640000
0"
#645000
b11 '
1"
#650000
0"
#655000
b100 '
1"
#660000
0"
#665000
b101 '
1"
#670000
0"
#675000
b110 '
1"
#680000
0"
#685000
b111 '
1"
#690000
0"
#695000
b1000 '
1"
#700000
0"
#705000
b1001 '
1"
#710000
0"
#715000
b1010 '
1"
#720000
0"
#725000
b1011 '
1"
#730000
0"
#735000
0!
b0 '
1"
#740000
0"
#745000
b1 '
1"
#750000
0"
#755000
b10 '
1"
#760000
0"
#765000
b11 '
1"
#770000
0"
#775000
b100 '
1"
#780000
0"
#785000
b101 '
1"
#790000
0"
#795000
b110 '
1"
#800000
0"
#805000
b111 '
1"
#810000
0"
#815000
b1000 '
1"
#820000
0"
#825000
b1001 '
1"
#830000
0"
#835000
b1010 '
1"
#840000
0"
#845000
b1011 '
1"
#850000
0"
#855000
1!
b0 '
1"
#860000
0"
#865000
b1 '
1"
#870000
0"
#875000
b10 '
1"
#880000
0"
#885000
b11 '
1"
#890000
0"
#895000
b100 '
1"
#900000
0"
#905000
b101 '
1"
#910000
0"
#915000
b110 '
1"
#920000
0"
#925000
b111 '
1"
#930000
0"
#935000
b1000 '
1"
#940000
0"
#945000
b1001 '
1"
#950000
0"
#955000
b1010 '
1"
#960000
0"
#965000
b1011 '
1"
#970000
0"
#975000
0!
b0 '
1"
#980000
0"
#985000
b1 '
1"
#990000
0"
#995000
b10 '
1"
#1000000
0"
#1005000
b11 '
1"
#1010000
0"
#1015000
b100 '
1"
